Metadata-Version: 2.1
Name: lattice-addons-pytorch
Version: 0.1.1
Summary: Lattice Add-ons
License: UNKNOWN
Platform: UNKNOWN
Requires-Python: >=3.7
Requires-Dist: torch
Requires-Dist: boto3
